pyfixtures/__init__.py
pyfixtures/_fixture.py
pyfixtures/_scope.py
pyfixtures/_utils.py
pyfixtures/errors.py
pyfixtures/sphinx/__init__.py
pyfixtures/sphinx/ext/__init__.py
pyfixtures/sphinx/ext/autofixture.py
pyfixtures-1.1.0.dist-info/LICENSE
pyfixtures-1.1.0.dist-info/WHEEL
pyfixtures-1.1.0.dist-info/METADATA
pyfixtures-1.1.0.dist-info/RECORD
