Metadata-Version: 2.1
Name: pyfixtures
Version: 1.1.0
Summary: Pytest style fixtures outside of Pytest.
Home-page: https://github.com/virtool/fixtures
License: MIT
Author: Ian Boyes
Requires-Python: >=3.8,<4.0
Classifier: License :: OSI Approved :: MIT License
Classifier: Programming Language :: Python :: 3
Classifier: Programming Language :: Python :: 3.10
Classifier: Programming Language :: Python :: 3.8
Classifier: Programming Language :: Python :: 3.9
Classifier: Topic :: Software Development :: Libraries
Project-URL: Repository, https://github.com/virtool/fixtures
